MANIFEST.in
README.md
requirements.txt
setup.py
keras_position_wise_feed_forward/__init__.py
keras_position_wise_feed_forward/feed_forward.py
keras_position_wise_feed_forward.egg-info/PKG-INFO
keras_position_wise_feed_forward.egg-info/SOURCES.txt
keras_position_wise_feed_forward.egg-info/dependency_links.txt
keras_position_wise_feed_forward.egg-info/requires.txt
keras_position_wise_feed_forward.egg-info/top_level.txt
tests/__init__.py
tests/test_feed_forward.py