Metadata-Version: 2.1
Name: keras-position-wise-feed-forward
Version: 0.8.0
Summary: Feed forward layer implemented in Keras
Home-page: https://github.com/CyberZHG/keras-position-wise-feed-forward
Author: CyberZHG
Author-email: CyberZHG@users.noreply.github.com
License: MIT
Platform: UNKNOWN
Classifier: Programming Language :: Python :: 3
Classifier: License :: OSI Approved :: MIT License
Classifier: Operating System :: OS Independent
